odoo/addons/l10n_es_vat_book/README.rst
odoo/addons/l10n_es_vat_book/__init__.py
odoo/addons/l10n_es_vat_book/__manifest__.py
odoo/addons/l10n_es_vat_book/data/aeat_vat_book_map_data.xml
odoo/addons/l10n_es_vat_book/i18n/bg.po
odoo/addons/l10n_es_vat_book/i18n/ca.po
odoo/addons/l10n_es_vat_book/i18n/cs.po
odoo/addons/l10n_es_vat_book/i18n/de.po
odoo/addons/l10n_es_vat_book/i18n/es.po
odoo/addons/l10n_es_vat_book/i18n/es_CO.po
odoo/addons/l10n_es_vat_book/i18n/es_CR.po
odoo/addons/l10n_es_vat_book/i18n/eu.po
odoo/addons/l10n_es_vat_book/i18n/fr.po
odoo/addons/l10n_es_vat_book/i18n/gl.po
odoo/addons/l10n_es_vat_book/i18n/hr.po
odoo/addons/l10n_es_vat_book/i18n/l10n_es_vat_book.pot
odoo/addons/l10n_es_vat_book/i18n/nl.po
odoo/addons/l10n_es_vat_book/i18n/pl.po
odoo/addons/l10n_es_vat_book/i18n/pt.po
odoo/addons/l10n_es_vat_book/i18n/pt_BR.po
odoo/addons/l10n_es_vat_book/i18n/ru.po
odoo/addons/l10n_es_vat_book/i18n/sl.po
odoo/addons/l10n_es_vat_book/i18n/sv.po
odoo/addons/l10n_es_vat_book/i18n/tr.po
odoo/addons/l10n_es_vat_book/i18n/vi.po
odoo/addons/l10n_es_vat_book/models/__init__.py
odoo/addons/l10n_es_vat_book/models/aeat_vat_book_map_line.py
odoo/addons/l10n_es_vat_book/models/l10n_es_vat_book.py
odoo/addons/l10n_es_vat_book/models/l10n_es_vat_book_line.py
odoo/addons/l10n_es_vat_book/models/l10n_es_vat_book_line_tax.py
odoo/addons/l10n_es_vat_book/models/l10n_es_vat_book_summary.py
odoo/addons/l10n_es_vat_book/models/l10n_es_vat_book_tax_summary.py
odoo/addons/l10n_es_vat_book/readme/CONFIGURE.rst
odoo/addons/l10n_es_vat_book/readme/CONTRIBUTORS.rst
odoo/addons/l10n_es_vat_book/readme/DESCRIPTION.rst
odoo/addons/l10n_es_vat_book/readme/INSTALL.rst
odoo/addons/l10n_es_vat_book/readme/ROADMAP.rst
odoo/addons/l10n_es_vat_book/readme/USAGE.rst
odoo/addons/l10n_es_vat_book/report/__init__.py
odoo/addons/l10n_es_vat_book/report/common_templates.xml
odoo/addons/l10n_es_vat_book/report/report_views.xml
odoo/addons/l10n_es_vat_book/report/vat_book_invoices_issued.xml
odoo11_addon_l10n_es_vat_book-11.0.3.4.0.dist-info/METADATA
odoo11_addon_l10n_es_vat_book-11.0.3.4.0.dist-info/WHEEL
odoo11_addon_l10n_es_vat_book-11.0.3.4.0.dist-info/top_level.txt
odoo11_addon_l10n_es_vat_book-11.0.3.4.0.dist-info/RECORD
